tests/gcloud/__init__.py
tests/gcloud/log_test.py
tests/integration/__init__.py
tests/integration/sentry_test.py
tidbits/__init__.py
tidbits/log.py
tidbits/gcloud/__init__.py
tidbits/gcloud/log.py
tidbits/integration/__init__.py
tidbits/integration/sentry.py
tidbits-0.4.1.dist-info/LICENSE
tidbits-0.4.1.dist-info/METADATA
tidbits-0.4.1.dist-info/WHEEL
tidbits-0.4.1.dist-info/top_level.txt
tidbits-0.4.1.dist-info/RECORD
