Metadata-Version: 2.1
Name: tidbits
Version: 0.4.1
Summary: Useful Python Tidbits
Home-page: https://github.com/TheKevJames/tidbits
Author: Kevin James
Author-email: KevinJames@thekev.in
License: MIT
Project-URL: Changelog, https://github.com/TheKevJames/tidbits/releases
Platform: UNKNOWN
Classifier: Development Status :: 4 - Beta
Classifier: Intended Audience :: Developers
Classifier: License :: OSI Approved :: MIT License
Classifier: Operating System :: OS Independent
Classifier: Programming Language :: Python
Classifier: Programming Language :: Python :: 2
Classifier: Programming Language :: Python :: 2.7
Classifier: Programming Language :: Python :: 3
Classifier: Programming Language :: Python :: 3.4
Classifier: Programming Language :: Python :: 3.5
Classifier: Programming Language :: Python :: 3.6
Classifier: Programming Language :: Python :: 3.7
Classifier: Topic :: Utilities
Provides-Extra: gcloud
Requires-Dist: python-json-logger (<1.0.0,>=0.1.0); extra == 'gcloud'
Provides-Extra: sentry
Requires-Dist: raven (<7.0.0,>=5.0.0); extra == 'sentry'
